{
	"archive" : {},
	"artifacts" : 
	[
		{
			"path" : "_deps/asp2-build/asp.lib"
		}
	],
	"backtrace" : 1,
	"backtraceGraph" : 
	{
		"commands" : 
		[
			"add_library",
			"install",
			"target_link_libraries",
			"add_compile_options",
			"target_compile_definitions",
			"target_include_directories"
		],
		"files" : 
		[
			"build/_deps/asp2-src/CMakeLists.txt",
			"C:/Users/jimin/Desktop/GDmods/geode/CMakeLists.txt"
		],
		"nodes" : 
		[
			{
				"file" : 0
			},
			{
				"command" : 0,
				"file" : 0,
				"line" : 45,
				"parent" : 0
			},
			{
				"command" : 1,
				"file" : 0,
				"line" : 71,
				"parent" : 0
			},
			{
				"command" : 2,
				"file" : 0,
				"line" : 62,
				"parent" : 0
			},
			{
				"file" : 1
			},
			{
				"command" : 3,
				"file" : 1,
				"line" : 233,
				"parent" : 4
			},
			{
				"command" : 4,
				"file" : 0,
				"line" : 63,
				"parent" : 0
			},
			{
				"command" : 4,
				"file" : 0,
				"line" : 49,
				"parent" : 0
			},
			{
				"command" : 5,
				"file" : 0,
				"line" : 65,
				"parent" : 0
			}
		]
	},
	"codemodelVersion" : 
	{
		"major" : 2,
		"minor" : 10
	},
	"compileDependencies" : 
	[
		{
			"backtrace" : 3,
			"id" : "GeodeResult::@7c2918d2800bad6c4b52"
		},
		{
			"backtrace" : 3,
			"id" : "fmt::@976f4f0bee90b99ecdb6"
		},
		{
			"backtrace" : 3,
			"id" : "nontype_functional::@ea86fd96e7b9184e2565"
		}
	],
	"compileGroups" : 
	[
		{
			"compileCommandFragments" : 
			[
				{
					"fragment" : "-O0 -g -Xclang -gcodeview -std=gnu++23 -D_DEBUG -D_DLL -D_MT -Xclang --dependent-lib=msvcrtd"
				},
				{
					"backtrace" : 5,
					"fragment" : "--target=x86_64-pc-windows-msvc"
				}
			],
			"defines" : 
			[
				{
					"backtrace" : 6,
					"define" : "NOMINMAX=1"
				},
				{
					"backtrace" : 7,
					"define" : "_HAS_ITERATOR_DEBUGGING=0"
				}
			],
			"includes" : 
			[
				{
					"backtrace" : 8,
					"path" : "C:/Users/jimin/Desktop/GDmods/ShowcaseMod/mod folder/Showcase Mod/build/_deps/asp2-src/include"
				},
				{
					"backtrace" : 3,
					"isSystem" : true,
					"path" : "C:/Users/jimin/Desktop/GDmods/ShowcaseMod/mod folder/Showcase Mod/build/_deps/result-src/include"
				},
				{
					"backtrace" : 3,
					"isSystem" : true,
					"path" : "C:/Users/jimin/Desktop/GDmods/ShowcaseMod/mod folder/Showcase Mod/build/_deps/fmt-src/include"
				},
				{
					"backtrace" : 3,
					"isSystem" : true,
					"path" : "C:/Users/jimin/Desktop/GDmods/ShowcaseMod/mod folder/Showcase Mod/build/_deps/nontype_functional-src/include"
				}
			],
			"language" : "CXX",
			"languageStandard" : 
			{
				"backtraces" : 
				[
					3,
					3,
					3
				],
				"standard" : "23"
			},
			"sourceIndexes" : 
			[
				0
			]
		}
	],
	"dependencies" : 
	[
		{
			"backtrace" : 3,
			"id" : "fmt::@976f4f0bee90b99ecdb6"
		}
	],
	"id" : "asp::@923cebb4b49503e63f6c",
	"install" : 
	{
		"destinations" : 
		[
			{
				"backtrace" : 2,
				"path" : "lib"
			}
		],
		"prefix" : 
		{
			"path" : "C:/Program Files (x86)/ShowcaseMod"
		}
	},
	"interfaceCompileDependencies" : 
	[
		{
			"backtrace" : 3,
			"id" : "GeodeResult::@7c2918d2800bad6c4b52"
		},
		{
			"backtrace" : 3,
			"id" : "fmt::@976f4f0bee90b99ecdb6"
		},
		{
			"backtrace" : 3,
			"id" : "nontype_functional::@ea86fd96e7b9184e2565"
		}
	],
	"interfaceLinkLibraries" : 
	[
		{
			"backtrace" : 3,
			"id" : "GeodeResult::@7c2918d2800bad6c4b52"
		},
		{
			"backtrace" : 3,
			"id" : "fmt::@976f4f0bee90b99ecdb6"
		},
		{
			"backtrace" : 3,
			"id" : "nontype_functional::@ea86fd96e7b9184e2565"
		}
	],
	"linkLibraries" : 
	[
		{
			"backtrace" : 3,
			"id" : "GeodeResult::@7c2918d2800bad6c4b52"
		},
		{
			"backtrace" : 3,
			"id" : "fmt::@976f4f0bee90b99ecdb6"
		},
		{
			"backtrace" : 3,
			"id" : "nontype_functional::@ea86fd96e7b9184e2565"
		}
	],
	"name" : "asp",
	"nameOnDisk" : "asp.lib",
	"paths" : 
	{
		"build" : "_deps/asp2-build",
		"source" : "build/_deps/asp2-src"
	},
	"sourceGroups" : 
	[
		{
			"name" : "Source Files",
			"sourceIndexes" : 
			[
				0,
				58,
				59,
				60,
				61,
				62,
				63,
				64,
				65,
				66,
				67
			]
		},
		{
			"name" : "Header Files",
			"sourceIndexes" : 
			[
				1,
				2,
				3,
				4,
				5,
				6,
				7,
				8,
				9,
				10,
				11,
				12,
				13,
				14,
				15,
				16,
				17,
				18,
				19,
				20,
				21,
				22,
				23,
				24,
				25,
				26,
				27,
				28,
				29,
				30,
				31,
				32,
				33,
				34,
				35,
				36,
				37,
				38,
				39,
				40,
				41,
				42,
				43,
				44,
				45,
				46,
				47,
				48,
				49,
				50,
				51,
				52,
				53,
				54,
				55,
				56,
				57,
				68,
				69,
				70,
				71
			]
		}
	],
	"sources" : 
	[
		{
			"backtrace" : 0,
			"compileGroupIndex" : 0,
			"path" : "build/_deps/asp2-build/CMakeFiles/asp.dir/Unity/unity_0_cxx.cxx",
			"sourceGroupIndex" : 0
		},
		{
			"backtrace" : 1,
			"path" : "build/_deps/asp2-src/include/asp/Log.hpp",
			"sourceGroupIndex" : 1
		},
		{
			"backtrace" : 1,
			"path" : "build/_deps/asp2-src/include/asp/collections.hpp",
			"sourceGroupIndex" : 1
		},
		{
			"backtrace" : 1,
			"path" : "build/_deps/asp2-src/include/asp/collections/SmallVec.hpp",
			"sourceGroupIndex" : 1
		},
		{
			"backtrace" : 1,
			"path" : "build/_deps/asp2-src/include/asp/data.hpp",
			"sourceGroupIndex" : 1
		},
		{
			"backtrace" : 1,
			"path" : "build/_deps/asp2-src/include/asp/data/Cow.hpp",
			"sourceGroupIndex" : 1
		},
		{
			"backtrace" : 1,
			"path" : "build/_deps/asp2-src/include/asp/data/nums.hpp",
			"sourceGroupIndex" : 1
		},
		{
			"backtrace" : 1,
			"path" : "build/_deps/asp2-src/include/asp/data/util.hpp",
			"sourceGroupIndex" : 1
		},
		{
			"backtrace" : 1,
			"path" : "build/_deps/asp2-src/include/asp/detail/Function.hpp",
			"sourceGroupIndex" : 1
		},
		{
			"backtrace" : 1,
			"path" : "build/_deps/asp2-src/include/asp/detail/Result.hpp",
			"sourceGroupIndex" : 1
		},
		{
			"backtrace" : 1,
			"path" : "build/_deps/asp2-src/include/asp/detail/config.hpp",
			"sourceGroupIndex" : 1
		},
		{
			"backtrace" : 1,
			"path" : "build/_deps/asp2-src/include/asp/format.hpp",
			"sourceGroupIndex" : 1
		},
		{
			"backtrace" : 1,
			"path" : "build/_deps/asp2-src/include/asp/fs.hpp",
			"sourceGroupIndex" : 1
		},
		{
			"backtrace" : 1,
			"path" : "build/_deps/asp2-src/include/asp/fs/Error.hpp",
			"sourceGroupIndex" : 1
		},
		{
			"backtrace" : 1,
			"path" : "build/_deps/asp2-src/include/asp/fs/fs.hpp",
			"sourceGroupIndex" : 1
		},
		{
			"backtrace" : 1,
			"path" : "build/_deps/asp2-src/include/asp/iter.hpp",
			"sourceGroupIndex" : 1
		},
		{
			"backtrace" : 1,
			"path" : "build/_deps/asp2-src/include/asp/iter/ArrayChunks.hpp",
			"sourceGroupIndex" : 1
		},
		{
			"backtrace" : 1,
			"path" : "build/_deps/asp2-src/include/asp/iter/Chain.hpp",
			"sourceGroupIndex" : 1
		},
		{
			"backtrace" : 1,
			"path" : "build/_deps/asp2-src/include/asp/iter/Copied.hpp",
			"sourceGroupIndex" : 1
		},
		{
			"backtrace" : 1,
			"path" : "build/_deps/asp2-src/include/asp/iter/Cycle.hpp",
			"sourceGroupIndex" : 1
		},
		{
			"backtrace" : 1,
			"path" : "build/_deps/asp2-src/include/asp/iter/Filter.hpp",
			"sourceGroupIndex" : 1
		},
		{
			"backtrace" : 1,
			"path" : "build/_deps/asp2-src/include/asp/iter/FilterMap.hpp",
			"sourceGroupIndex" : 1
		},
		{
			"backtrace" : 1,
			"path" : "build/_deps/asp2-src/include/asp/iter/Inspect.hpp",
			"sourceGroupIndex" : 1
		},
		{
			"backtrace" : 1,
			"path" : "build/_deps/asp2-src/include/asp/iter/Iter.hpp",
			"sourceGroupIndex" : 1
		},
		{
			"backtrace" : 1,
			"path" : "build/_deps/asp2-src/include/asp/iter/Map.hpp",
			"sourceGroupIndex" : 1
		},
		{
			"backtrace" : 1,
			"path" : "build/_deps/asp2-src/include/asp/iter/Skip.hpp",
			"sourceGroupIndex" : 1
		},
		{
			"backtrace" : 1,
			"path" : "build/_deps/asp2-src/include/asp/iter/Split.hpp",
			"sourceGroupIndex" : 1
		},
		{
			"backtrace" : 1,
			"path" : "build/_deps/asp2-src/include/asp/iter/Take.hpp",
			"sourceGroupIndex" : 1
		},
		{
			"backtrace" : 1,
			"path" : "build/_deps/asp2-src/include/asp/iter/Zip.hpp",
			"sourceGroupIndex" : 1
		},
		{
			"backtrace" : 1,
			"path" : "build/_deps/asp2-src/include/asp/iter/std.hpp",
			"sourceGroupIndex" : 1
		},
		{
			"backtrace" : 1,
			"path" : "build/_deps/asp2-src/include/asp/math.hpp",
			"sourceGroupIndex" : 1
		},
		{
			"backtrace" : 1,
			"path" : "build/_deps/asp2-src/include/asp/math/NumberCycle.hpp",
			"sourceGroupIndex" : 1
		},
		{
			"backtrace" : 1,
			"path" : "build/_deps/asp2-src/include/asp/misc.hpp",
			"sourceGroupIndex" : 1
		},
		{
			"backtrace" : 1,
			"path" : "build/_deps/asp2-src/include/asp/misc/traits.hpp",
			"sourceGroupIndex" : 1
		},
		{
			"backtrace" : 1,
			"path" : "build/_deps/asp2-src/include/asp/net.hpp",
			"sourceGroupIndex" : 1
		},
		{
			"backtrace" : 1,
			"path" : "build/_deps/asp2-src/include/asp/ptr.hpp",
			"sourceGroupIndex" : 1
		},
		{
			"backtrace" : 1,
			"path" : "build/_deps/asp2-src/include/asp/ptr/BoxedString.hpp",
			"sourceGroupIndex" : 1
		},
		{
			"backtrace" : 1,
			"path" : "build/_deps/asp2-src/include/asp/ptr/PtrSwap.hpp",
			"sourceGroupIndex" : 1
		},
		{
			"backtrace" : 1,
			"path" : "build/_deps/asp2-src/include/asp/ptr/SharedPtr.hpp",
			"sourceGroupIndex" : 1
		},
		{
			"backtrace" : 1,
			"path" : "build/_deps/asp2-src/include/asp/simd.hpp",
			"sourceGroupIndex" : 1
		},
		{
			"backtrace" : 1,
			"path" : "build/_deps/asp2-src/include/asp/simd/CPUFeatures.hpp",
			"sourceGroupIndex" : 1
		},
		{
			"backtrace" : 1,
			"path" : "build/_deps/asp2-src/include/asp/simd/base.hpp",
			"sourceGroupIndex" : 1
		},
		{
			"backtrace" : 1,
			"path" : "build/_deps/asp2-src/include/asp/sync.hpp",
			"sourceGroupIndex" : 1
		},
		{
			"backtrace" : 1,
			"path" : "build/_deps/asp2-src/include/asp/sync/Channel.hpp",
			"sourceGroupIndex" : 1
		},
		{
			"backtrace" : 1,
			"path" : "build/_deps/asp2-src/include/asp/sync/Mutex.hpp",
			"sourceGroupIndex" : 1
		},
		{
			"backtrace" : 1,
			"path" : "build/_deps/asp2-src/include/asp/sync/Notify.hpp",
			"sourceGroupIndex" : 1
		},
		{
			"backtrace" : 1,
			"path" : "build/_deps/asp2-src/include/asp/sync/SpinLock.hpp",
			"sourceGroupIndex" : 1
		},
		{
			"backtrace" : 1,
			"path" : "build/_deps/asp2-src/include/asp/thread.hpp",
			"sourceGroupIndex" : 1
		},
		{
			"backtrace" : 1,
			"path" : "build/_deps/asp2-src/include/asp/thread/Thread.hpp",
			"sourceGroupIndex" : 1
		},
		{
			"backtrace" : 1,
			"path" : "build/_deps/asp2-src/include/asp/thread/ThreadPool.hpp",
			"sourceGroupIndex" : 1
		},
		{
			"backtrace" : 1,
			"path" : "build/_deps/asp2-src/include/asp/time.hpp",
			"sourceGroupIndex" : 1
		},
		{
			"backtrace" : 1,
			"path" : "build/_deps/asp2-src/include/asp/time/DateTime.hpp",
			"sourceGroupIndex" : 1
		},
		{
			"backtrace" : 1,
			"path" : "build/_deps/asp2-src/include/asp/time/Duration.hpp",
			"sourceGroupIndex" : 1
		},
		{
			"backtrace" : 1,
			"path" : "build/_deps/asp2-src/include/asp/time/Instant.hpp",
			"sourceGroupIndex" : 1
		},
		{
			"backtrace" : 1,
			"path" : "build/_deps/asp2-src/include/asp/time/SystemTime.hpp",
			"sourceGroupIndex" : 1
		},
		{
			"backtrace" : 1,
			"path" : "build/_deps/asp2-src/include/asp/time/chrono.hpp",
			"sourceGroupIndex" : 1
		},
		{
			"backtrace" : 1,
			"path" : "build/_deps/asp2-src/include/asp/time/detail.hpp",
			"sourceGroupIndex" : 1
		},
		{
			"backtrace" : 1,
			"path" : "build/_deps/asp2-src/include/asp/time/sleep.hpp",
			"sourceGroupIndex" : 1
		},
		{
			"backtrace" : 1,
			"path" : "build/_deps/asp2-src/src/Log.cpp",
			"sourceGroupIndex" : 0
		},
		{
			"backtrace" : 1,
			"path" : "build/_deps/asp2-src/src/assert.cpp",
			"sourceGroupIndex" : 0
		},
		{
			"backtrace" : 1,
			"path" : "build/_deps/asp2-src/src/fs/fs.cpp",
			"sourceGroupIndex" : 0
		},
		{
			"backtrace" : 1,
			"path" : "build/_deps/asp2-src/src/platform/windows/Notify.cpp",
			"sourceGroupIndex" : 0
		},
		{
			"backtrace" : 1,
			"path" : "build/_deps/asp2-src/src/simd/x86/CPUFeaturesX86.cpp",
			"sourceGroupIndex" : 0
		},
		{
			"backtrace" : 1,
			"path" : "build/_deps/asp2-src/src/thread/Thread.cpp",
			"sourceGroupIndex" : 0
		},
		{
			"backtrace" : 1,
			"path" : "build/_deps/asp2-src/src/thread/ThreadPool.cpp",
			"sourceGroupIndex" : 0
		},
		{
			"backtrace" : 1,
			"path" : "build/_deps/asp2-src/src/time/Duration.cpp",
			"sourceGroupIndex" : 0
		},
		{
			"backtrace" : 1,
			"path" : "build/_deps/asp2-src/src/time/Instant.cpp",
			"sourceGroupIndex" : 0
		},
		{
			"backtrace" : 1,
			"path" : "build/_deps/asp2-src/src/time/SystemTime.cpp",
			"sourceGroupIndex" : 0
		},
		{
			"backtrace" : 3,
			"path" : "build/_deps/nontype_functional-src/include/std23/function_ref.h",
			"sourceGroupIndex" : 1
		},
		{
			"backtrace" : 3,
			"path" : "build/_deps/nontype_functional-src/include/std23/function.h",
			"sourceGroupIndex" : 1
		},
		{
			"backtrace" : 3,
			"path" : "build/_deps/nontype_functional-src/include/std23/move_only_function.h",
			"sourceGroupIndex" : 1
		},
		{
			"backtrace" : 3,
			"path" : "build/_deps/nontype_functional-src/include/std23/__functional_base.h",
			"sourceGroupIndex" : 1
		}
	],
	"type" : "STATIC_LIBRARY"
}
