{
	"backtrace" : 5,
	"backtraceGraph" : 
	{
		"commands" : 
		[
			"add_custom_target",
			"include"
		],
		"files" : 
		[
			"C:/Program Files/CMake/share/cmake-4.3/Modules/CTestTargets.cmake",
			"C:/Program Files/CMake/share/cmake-4.3/Modules/CTest.cmake",
			"build/_deps/nontype_functional-src/CMakeLists.txt"
		],
		"nodes" : 
		[
			{
				"file" : 2
			},
			{
				"command" : 1,
				"file" : 2,
				"line" : 22,
				"parent" : 0
			},
			{
				"file" : 1,
				"parent" : 1
			},
			{
				"command" : 1,
				"file" : 1,
				"line" : 277,
				"parent" : 2
			},
			{
				"file" : 0,
				"parent" : 3
			},
			{
				"command" : 0,
				"file" : 0,
				"line" : 96,
				"parent" : 4
			}
		]
	},
	"codemodelVersion" : 
	{
		"major" : 2,
		"minor" : 10
	},
	"folder" : 
	{
		"name" : "CTestDashboardTargets"
	},
	"id" : "ExperimentalStart::@ea86fd96e7b9184e2565",
	"name" : "ExperimentalStart",
	"paths" : 
	{
		"build" : "_deps/nontype_functional-build",
		"source" : "build/_deps/nontype_functional-src"
	},
	"sourceGroups" : 
	[
		{
			"name" : "",
			"sourceIndexes" : 
			[
				0
			]
		},
		{
			"name" : "CMake Rules",
			"sourceIndexes" : 
			[
				1
			]
		}
	],
	"sources" : 
	[
		{
			"backtrace" : 5,
			"isGenerated" : true,
			"path" : "build/_deps/nontype_functional-build/CMakeFiles/ExperimentalStart",
			"sourceGroupIndex" : 0
		},
		{
			"backtrace" : 0,
			"isGenerated" : true,
			"path" : "build/_deps/nontype_functional-build/CMakeFiles/ExperimentalStart.rule",
			"sourceGroupIndex" : 1
		}
	],
	"type" : "UTILITY"
}
